plux/__init__.py
plux/__main__.py
plux/version.py
plux/build/__init__.py
plux/build/config.py
plux/build/discovery.py
plux/build/hatchling.py
plux/build/index.py
plux/build/project.py
plux/build/setuptools.py
plux/cli/__init__.py
plux/cli/cli.py
plux/core/__init__.py
plux/core/entrypoint.py
plux/core/plugin.py
plux/runtime/__init__.py
plux/runtime/cache.py
plux/runtime/filter.py
plux/runtime/manager.py
plux/runtime/metadata.py
plux/runtime/resolve.py
plux-1.14.0.dist-info/METADATA
plux-1.14.0.dist-info/WHEEL
plux-1.14.0.dist-info/entry_points.txt
plux-1.14.0.dist-info/licenses/LICENSE
plux-1.14.0.dist-info/RECORD
