Metadata-Version: 2.4
Name: plux
Version: 1.14.0
Summary: A dynamic code loading framework for building pluggable Python distributions
Project-URL: Repository, https://github.com/localstack/plux
Author-email: Thomas Rausch <info@localstack.cloud>
License-Expression: Apache-2.0
License-File: LICENSE
Classifier: Development Status :: 5 - Production/Stable
Classifier: Operating System :: OS Independent
Classifier: Programming Language :: Python :: 3
Classifier: Programming Language :: Python :: 3.10
Classifier: Programming Language :: Python :: 3.11
Classifier: Programming Language :: Python :: 3.12
Classifier: Programming Language :: Python :: 3.13
Classifier: Topic :: Software Development :: Libraries
Classifier: Topic :: Utilities
Requires-Python: >=3.10
Provides-Extra: dev
Requires-Dist: build; extra == 'dev'
Requires-Dist: pytest==8.4.1; extra == 'dev'
Requires-Dist: ruff==0.9.1; extra == 'dev'
Requires-Dist: setuptools; extra == 'dev'
